[{"Name":"Aires acondicionandos","Quantity":10,"Cost":100,"Location":{"Found":true,"AddresLine":"Avenida General Jos\u00E9 Garibaldi 2313","CountryRegion":"Uruguay","FormattedAddress":"Avenida General Jos\u00E9 Garibaldi 2313, Montevideo, 11800","Locality":"Montevideo","PostalCode":"11800","Latitude":-34.8833,"Longitude":-56.1675},"Availability":false,"RegularOffers":false,"Tags":[],"DeliveryDate":"0001-01-01T00:00:00","PublicationDate":"2021-11-29T19:11:50.0835493-03:00","Company":{"Name":"Google SA","Id":"1262655798","Location":{"Found":true,"AddresLine":"Calle Colorado 2326","CountryRegion":"Uruguay","FormattedAddress":"Calle Colorado 2326, Montevideo, 11800","Locality":"Montevideo","PostalCode":"11800","Latitude":-34.87832,"Longitude":-56.16779},"Phone":"4324546","AreaOfWork":{"Name":"construccion"}},"Material":{"Name":"Material pl\u00E1stico","Type":{"Name":"Plastico","Description":"Partes de aires acondicionados"},"Unit":"Ac"},"Offerpermissions":[],"Idd":1,"Entrepreneur":"1262655798"},{"Name":"Materiales de Construcci\u00F3n","Quantity":1,"Cost":300,"Location":{"Found":true,"AddresLine":"Avenida de Los Gauchos","CountryRegion":"Uruguay","FormattedAddress":"Avenida de Los Gauchos, Maldonado, Maldonado, 20000","Locality":"Maldonado","PostalCode":"20000","Latitude":-34.89015,"Longitude":-54.94171},"Availability":false,"RegularOffers":false,"Tags":[],"DeliveryDate":"0001-01-01T00:00:00","PublicationDate":"2021-11-29T19:53:34.6187734-03:00","Company":{"Name":"Google SA","Id":"1262655798","Location":{"Found":true,"AddresLine":"Calle Colorado 2326","CountryRegion":"Uruguay","FormattedAddress":"Calle Colorado 2326, Montevideo, 11800","Locality":"Montevideo","PostalCode":"11800","Latitude":-34.87832,"Longitude":-56.16779},"Phone":"4324546","AreaOfWork":{"Name":"construccion"}},"Material":{"Name":"Pedregullo","Type":{"Name":"Escombro","Description":"Material de relleno"},"Unit":"Piedra"},"Offerpermissions":[],"Idd":2,"Entrepreneur":"1262655798"}]